uscensus/__init__.py
uscensus/data/__init__.py
uscensus/data/discovery.py
uscensus/data/model.py
uscensus/data/states.py
uscensus/geocode/__init__.py
uscensus/geocode/bulk.py
uscensus/tests/__init__.py
uscensus/tests/dbapicache.py
uscensus/tests/dbapiqueryhelper.py
uscensus/tests/discovery.py
uscensus/tests/errors.py
uscensus/tests/geocode.py
uscensus/tests/model.py
uscensus/tests/nopcache.py
uscensus/tests/sqlalchemycache.py
uscensus/tests/webcache.py
uscensus/tests/whooshindex.py
uscensus/tiger/__init__.py
uscensus/util/__init__.py
uscensus/util/dbapicache.py
uscensus/util/dbapiqueryhelper.py
uscensus/util/ensuretext.py
uscensus/util/errors.py
uscensus/util/nopcache.py
uscensus/util/sqlalchemycache.py
uscensus/util/webcache.py
uscensus/util/textindex/__init__.py
uscensus/util/textindex/mongoindex.py
uscensus/util/textindex/sqlitefts5index.py
uscensus/util/textindex/textindexbase.py
uscensus/util/textindex/whooshindex.py
uscensus-0.2.4.dist-info/LICENSE.txt
uscensus-0.2.4.dist-info/METADATA
uscensus-0.2.4.dist-info/WHEEL
uscensus-0.2.4.dist-info/top_level.txt
uscensus-0.2.4.dist-info/RECORD
