Metadata-Version: 2.1
Name: uscensus
Version: 0.2.4
Summary: US Census API discovery wrappers
Home-page: https://github.com/nkrishnaswami/uscensus
Author: Natarajan Krishnaswami
Author-email: nkrish@acm.org
License: Apache Software License 2.0
Keywords: census demographics economics data api discovery
Platform: UNKNOWN
Classifier: Development Status :: 3 - Alpha
Classifier: Intended Audience :: Developers
Classifier: Intended Audience :: Science/Research
Classifier: License :: OSI Approved :: Apache Software License
Classifier: Operating System :: OS Independent
Classifier: Programming Language :: Python
Classifier: Topic :: Sociology
Classifier: Topic :: Scientific/Engineering :: GIS
Requires-Dist: docutils (>=0.3)
Requires-Dist: python-dateutil
Requires-Dist: fiona
Requires-Dist: geopandas
Requires-Dist: httpx (>=0.17.0)
Requires-Dist: numpy
Requires-Dist: pandas
Requires-Dist: pymongo
Requires-Dist: pytz
Requires-Dist: requests
Requires-Dist: shapely
Requires-Dist: sqlalchemy
Requires-Dist: supersqlite
Requires-Dist: whoosh
